pai_mlflow/__init__.py
pai_mlflow/consts.py
pai_mlflow/exceptions.py
pai_mlflow/store/__init__.py
pai_mlflow/store/artifact/__init__.py
pai_mlflow/store/artifact/oss_artifact_repo.py
pai_mlflow/store/model_registry/__init__.py
pai_mlflow/store/model_registry/_convert_utils.py
pai_mlflow/store/model_registry/pai_store.py
pai_mlflow/store/tracking/__init__.py
pai_mlflow/store/tracking/_convert_utils.py
pai_mlflow/store/tracking/pai_rest_store.py
pai_mlflow/store/tracking/pai_store.py
pai_mlflow/store/tracking/context/__init__.py
pai_mlflow/store/tracking/context/paiflow_context.py
pai_mlflow/utils/__global.py
pai_mlflow/utils/__init__.py
pai_mlflow/utils/ai_workspace_utils.py
pai_mlflow/utils/mlflow_tags.py
pai_mlflow/utils/model_utils.py
pai_mlflow/vendor/__init__.py
pai_mlflow/vendor/alibabacloud_mlflow20210312/__init__.py
pai_mlflow/vendor/alibabacloud_mlflow20210312/client.py
pai_mlflow/vendor/alibabacloud_mlflow20210312/models.py
pai_mlflow_test-0.0.1.dist-info/LICENSE
pai_mlflow_test-0.0.1.dist-info/METADATA
pai_mlflow_test-0.0.1.dist-info/WHEEL
pai_mlflow_test-0.0.1.dist-info/entry_points.txt
pai_mlflow_test-0.0.1.dist-info/top_level.txt
pai_mlflow_test-0.0.1.dist-info/RECORD
