Metadata-Version: 2.1
Name: pai-mlflow-test
Version: 0.0.1
Summary: Alibaba Cloud PAI MLflow Plugin
Home-page: https://code.alibaba-inc.com/PAI/pai-mlflow-plugin
License: Apache License 2.0
Requires-Python: >=3.6
License-File: LICENSE
Requires-Dist: mlflow
Requires-Dist: oss2
Requires-Dist: alibabacloud-tea-util <1.0.0,>=0.3.3
Requires-Dist: alibabacloud-tea-openapi <1.0.0,>=0.2.4
Requires-Dist: alibabacloud-openapi-util <1.0.0,>=0.1.4
Requires-Dist: alibabacloud-endpoint-util <1.0.0,>=0.0.3
